solitude/__init__.py
solitude/cache.py
solitude/cli.py
solitude/commands.py
solitude/config.py
solitude/core.py
solitude/hookspecs.py
solitude/log.py
solitude/slurmjob.py
solitude/plugins/__init__.py
solitude/plugins/csubmit.py
solitude/plugins/default.py
solitude/plugins/interactive.py
solitude/utils/__init__.py
solitude/utils/ssh.py
solitude-0.3.9.dist-info/LICENSE
solitude-0.3.9.dist-info/METADATA
solitude-0.3.9.dist-info/WHEEL
solitude-0.3.9.dist-info/entry_points.txt
solitude-0.3.9.dist-info/top_level.txt
solitude-0.3.9.dist-info/RECORD
