Metadata-Version: 2.1
Name: solitude
Version: 0.3.9
Summary: A simple light-weight extendable command line tool for managing jobs on DIAG's SOL cluster.
Author: S.C. van de Leemput
Author-email: sil.vandeleemput@radboudumc.nl
License: LICENSE
Platform: UNKNOWN
Classifier: License :: OSI Approved :: Apache Software License
Classifier: Programming Language :: Python :: 3
Classifier: Intended Audience :: Science/Research
Classifier: Operating System :: OS Independent
License-File: LICENSE
Requires-Dist: appdirs
Requires-Dist: click
Requires-Dist: paramiko
Requires-Dist: pluggy
Requires-Dist: tqdm
